{"2017":{"bike_fatalities":0,"bike_severe_injuries":1,"motorcycle_fatalities":0,"motorcycle_severe_injuries":0,"motorist_fatalities":7,"motorist_severe_injuries":62,"pedestrian_fatalities":0,"pedestrian_severe_injuries":5,"total_fatalities":7,"total_severe_injuries":68},"2018":{"bike_fatalities":0,"bike_severe_injuries":0,"motorcycle_fatalities":0,"motorcycle_severe_injuries":1,"motorist_fatalities":5,"motorist_severe_injuries":54,"pedestrian_fatalities":1,"pedestrian_severe_injuries":2,"total_fatalities":6,"total_severe_injuries":57},"2019":{"bike_fatalities":0,"bike_severe_injuries":0,"motorcycle_fatalities":0,"motorcycle_severe_injuries":0,"motorist_fatalities":5,"motorist_severe_injuries":32,"pedestrian_fatalities":0,"pedestrian_severe_injuries":10,"total_fatalities":5,"total_severe_injuries":42},"2020":{"bike_fatalities":1,"bike_severe_injuries":0,"motorcycle_fatalities":0,"motorcycle_severe_injuries":0,"motorist_fatalities":3,"motorist_severe_injuries":39,"pedestrian_fatalities":1,"pedestrian_severe_injuries":2,"total_fatalities":5,"total_severe_injuries":41},"2021":{"bike_fatalities":0,"bike_severe_injuries":0,"motorcycle_fatalities":0,"motorcycle_severe_injuries":0,"motorist_fatalities":2,"motorist_severe_injuries":34,"pedestrian_fatalities":3,"pedestrian_severe_injuries":1,"total_fatalities":5,"total_severe_injuries":35},"2022":{"bike_fatalities":0,"bike_severe_injuries":0,"motorcycle_fatalities":0,"motorcycle_severe_injuries":0,"motorist_fatalities":4,"motorist_severe_injuries":48,"pedestrian_fatalities":2,"pedestrian_severe_injuries":7,"total_fatalities":6,"total_severe_injuries":55},"2023":{"bike_fatalities":0,"bike_severe_injuries":0,"motorcycle_fatalities":0,"motorcycle_severe_injuries":0,"motorist_fatalities":9,"motorist_severe_injuries":70,"pedestrian_fatalities":1,"pedestrian_severe_injuries":7,"total_fatalities":10,"total_severe_injuries":77},"2024":{"bike_fatalities":0,"bike_severe_injuries":0,"motorcycle_fatalities":0,"motorcycle_severe_injuries":0,"motorist_fatalities":2,"motorist_severe_injuries":18,"pedestrian_fatalities":0,"pedestrian_severe_injuries":0,"total_fatalities":2,"total_severe_injuries":18}}
